drisk_api-0.0.9.dist-info/METADATA
drisk_api-0.0.9.dist-info/WHEEL
drisk_api-0.0.9.dist-info/licenses/LICENSE
drisk_api/graph_client.py
drisk_api/__init__.py
drisk_api/interfaces/nx.py
drisk_api/drisk_api.cpython-39-arm-linux-gnueabihf.so
drisk_api-0.0.9.dist-info/RECORD
