Metadata-Version: 2.3
Name: drisk_api
Version: 0.0.9
Classifier: Programming Language :: Rust
Classifier: Programming Language :: Python :: Implementation :: CPython
Classifier: Programming Language :: Python :: Implementation :: PyPy
Requires-Dist: requests
License-File: LICENSE
Summary: drisk_api - API to connect to dRISK Edge.
Keywords: drisk
Home-Page: https://github.com/driskai/drisk_api
License: MIT
Requires-Python: >=3.8
Project-URL: Homepage, https://github.com/driskai/drisk_api/tree/main
Project-URL: Edge, https://demo.drisk.ai/
Project-URL: Edge Docs, https://demo.drisk.ai/docs/
